shubh_whatsapp/__init__.py
shubh_whatsapp/api_client.py
shubh_whatsapp/bridge.py
shubh_whatsapp/client.py
shubh_whatsapp/config.py
shubh_whatsapp/db_reader.py
shubh_whatsapp/exceptions.py
shubh_whatsapp-0.1.0.dist-info/licenses/LICENSE.md
shubh_whatsapp-0.1.0.dist-info/METADATA
shubh_whatsapp-0.1.0.dist-info/WHEEL
shubh_whatsapp-0.1.0.dist-info/top_level.txt
shubh_whatsapp-0.1.0.dist-info/RECORD
