Metadata-Version: 2.4
Name: shubh_whatsapp
Version: 0.1.0
Summary: Python wrapper for interacting with WhatsApp via the whatsapp-mcp Go bridge.
Author-email: Shubh <tanishkaishubh@gmail.com>
Project-URL: Homepage, https://github.com/Tanishk/shubh_whatsapp
Project-URL: Repository, https://github.com/Tanishk/shubh_whatsapp
Keywords: whatsapp,api,unofficial,wrapper,mcp
Classifier: Development Status :: 3 - Alpha
Classifier: Intended Audience :: Developers
Classifier: License :: OSI Approved :: MIT License
Classifier: Programming Language :: Python :: 3
Classifier: Programming Language :: Python :: 3.8
Classifier: Programming Language :: Python :: 3.9
Classifier: Programming Language :: Python :: 3.10
Classifier: Programming Language :: Python :: 3.11
Classifier: Operating System :: OS Independent
Classifier: Topic :: Communications :: Chat
Requires-Python: >=3.8
License-File: LICENSE.md
Requires-Dist: requests>=2.25.0
Dynamic: license-file
